what_the_face_classification/__init__.py
what_the_face_classification/active_model.pth
what_the_face_classification/haarcascade_frontalface_default.xml
what_the_face_classification/inference.py
what_the_face_classification/last_active_model.pth
what_the_face_classification/model.py
what_the_face_classification-0.0.27.dist-info/METADATA
what_the_face_classification-0.0.27.dist-info/WHEEL
what_the_face_classification-0.0.27.dist-info/licenses/LICENSE
what_the_face_classification-0.0.27.dist-info/RECORD
