Metadata-Version: 2.1
Name: what_the_face_classification
Version: 0.0.27
Summary: CNN image classification trained on FER2013 for the 7 emotion categories. 
Project-URL: Homepage, https://gitlab.com/jms.rdgrs/inference_package
Author-email: James Rodgers <jms.rdgrs@gmail.com>
License-File: LICENSE
Classifier: License :: OSI Approved :: MIT License
Classifier: Operating System :: OS Independent
Classifier: Programming Language :: Python :: 3
Requires-Python: >=3.7
Requires-Dist: numpy
Requires-Dist: opencv-python
Requires-Dist: pillow
Requires-Dist: setuptools
Requires-Dist: torch
Requires-Dist: torchvision
